{
    "id": 20,
    "name": "Dragon de Komodo",
    "description": "Le Dragon de Komodo ou Varan de Komodo (Varanus komodoensis1) est une espèce de varan qui se rencontre dans les îles de Komodo, Rinca, Florès, Gili Motang et Gili Dasami en Indonésie centrale. Membre de la famille des varanidés, c'est la plus grande espèce vivante de lézard, avec une longueur moyenne 2,59 m et une masse d'environ 79 à 91 kg. Sa taille inhabituelle est parfois attribuée au gigantisme insulaire car il n'existe pas, dans son habitat naturel, d'autres animaux carnivores pouvant occuper ou partager sa niche écologique, ainsi qu'à ses faibles besoins en énergie.",
    "imagePath": "R.animals.images.unknown",
    "soundPath": "R.animals.sounds.dragondekomodo"
}
